tono/__init__.py
tono/__main__.py
tono/py.typed
tono/cli/__init__.py
tono/cli/commands/__init__.py
tono/lib/__init__.py
tono/lib/_agent.py
tono/lib/_docstrings.py
tono/lib/_logging.py
tono/lib/_rich.py
tono/lib/base.py
tono/models/__init__.py
tono/models/anthropic/__init__.py
tono/models/anthropic/_client.py
tono/models/anthropic/_formatter.py
tono/models/openai/__init__.py
tono/models/openai/_client.py
tono/models/openai/_formatter.py
tono/tools/__init__.py
tono/tools/http.py
tono/tools/io.py
tono-0.1.3.dist-info/METADATA
tono-0.1.3.dist-info/WHEEL
tono-0.1.3.dist-info/entry_points.txt
tono-0.1.3.dist-info/licenses/LICENSE
tono-0.1.3.dist-info/RECORD
